CHANGELOG.txt
LICENCE.txt
MANIFEST.in
README.md
setup.py
CustomPyPong2/Pong.py
CustomPyPong2/__init__.py
CustomPyPong2.egg-info/PKG-INFO
CustomPyPong2.egg-info/SOURCES.txt
CustomPyPong2.egg-info/dependency_links.txt
CustomPyPong2.egg-info/requires.txt
CustomPyPong2.egg-info/top_level.txt