Metadata-Version: 2.4
Name: CustomPyPong2
Version: 0.0.1
Summary: Ping Pong package
Home-page: 
Author: Abhinav S Nair
Author-email: svnair.1984@gmail.com
License: MIT
Project-URL: Documentation, https://CustomPyPong2.readthedocs.io
Project-URL: Source, https://github.com/Sarish002/CustomPyPong2
Project-URL: Bug Tracker, https://github.com/Sarish002/CustomPyPong2/issues
Keywords: Table Tennis
Classifier: Development Status :: 5 - Production/Stable
Classifier: Intended Audience :: End Users/Desktop
Classifier: Operating System :: Microsoft :: Windows :: Windows 11
Classifier: License :: OSI Approved :: MIT License
Classifier: Programming Language :: Python :: 3
License-File: LICENCE.txt
Requires-Dist: Pygame
Dynamic: author
Dynamic: author-email
Dynamic: classifier
Dynamic: description
Dynamic: description-content-type
Dynamic: keywords
Dynamic: license
Dynamic: license-file
Dynamic: project-url
Dynamic: requires-dist
Dynamic: summary
